{
  "news": [
    {
      "photo": "https://avatars.mds.yandex.net/i?id=04eb918b184f06fecbf016f38d7b278f-5666076-images-thumbs&n=13",
      "describetion": "asdasdwqwdqwcqwcq",
      "name": "vwqvqwvqwv",
      "header": "as as as s sdvascqwcqwcwqcqwc",
      "id": 1
    },
    {
      "photo": "https://avatars.mds.yandex.net/i?id=04eb918b184f06fecbf016f38d7b278f-5666076-images-thumbs&n=13",
      "describetion": "wqvqwvwqvqwv",
      "name": "qwcwqqwcqwcwqc",
      "header": "qvqwvqwvqwv",
      "id": 2
    }
  ]
}